LICENSE
MANIFEST.in
README.md
setup.cfg
setup.py
epfs/__init__.py
epfs/admin.py
epfs/apps.py
epfs/forms.py
epfs/models.py
epfs/tests.py
epfs/urls.py
epfs/views.py
epfs.egg-info/PKG-INFO
epfs.egg-info/SOURCES.txt
epfs.egg-info/dependency_links.txt
epfs.egg-info/requires.txt
epfs.egg-info/top_level.txt
epfs/migrations/0001_initial.py
epfs/migrations/__init__.py
epfs/static/icon.png
epfs/static/manifest.json
epfs/static/service-worker.js
epfs/templates/epfs/sharefile.html