Metadata-Version: 2.1
Name: epfs
Version: 1.25
Summary: epfs is a Django app to sharing file.
Home-page: https://github.com/epg900/epfs.git
Author: epg
Author-email: epg900@gmail.com
License: GNU GENERAL PUBLIC LICENSE
Requires-Python: >=3.7
License-File: LICENSE
